agent/__init__.py
agent/browser_use/browser_use_agent.py
agent/deep_research/deep_research_agent.py
browser/__init__.py
browser/custom_browser.py
browser/custom_context.py
browseruse_web_ui-0.1.6.dist-info/licenses/LICENSE
controller/__init__.py
controller/custom_controller.py
utils/__init__.py
utils/config.py
utils/llm_provider.py
utils/mcp_client.py
utils/utils.py
webui/__init__.py
webui/interface.py
webui/webui.py
webui/webui_manager.py
webui/components/__init__.py
webui/components/agent_settings_tab.py
webui/components/browser_settings_tab.py
webui/components/browser_use_agent_tab.py
webui/components/deep_research_agent_tab.py
webui/components/load_save_config_tab.py
browseruse_web_ui-0.1.6.dist-info/METADATA
browseruse_web_ui-0.1.6.dist-info/WHEEL
browseruse_web_ui-0.1.6.dist-info/entry_points.txt
browseruse_web_ui-0.1.6.dist-info/top_level.txt
browseruse_web_ui-0.1.6.dist-info/RECORD
