Metadata-Version: 2.4
Name: browseruse-web-ui
Version: 0.1.6
Summary: Web UI for Browser-Use AI agents
Home-page: https://github.com/yourname/browser-use-web-ui
Author: Suleman
Author-email: Suleman <sulemanmuhamad049@gmail.com>
License: MIT
Classifier: Programming Language :: Python :: 3
Classifier: License :: OSI Approved :: MIT License
Classifier: Operating System :: OS Independent
Requires-Python: >=3.8
License-File: LICENSE
Requires-Dist: browser-use-agent>=0.1.48
Requires-Dist: pyperclip==1.9.0
Requires-Dist: gradio==5.27.0
Requires-Dist: json-repair
Requires-Dist: langchain-mistralai==0.2.4
Requires-Dist: MainContentExtractor==0.0.4
Requires-Dist: langchain-ibm==0.3.10
Requires-Dist: langchain_mcp_adapters==0.0.9
Requires-Dist: mcp==1.6.1
Requires-Dist: langgraph==0.3.34
Requires-Dist: langchain-community
Dynamic: author
Dynamic: home-page
Dynamic: license-file
Dynamic: requires-python
